neuralengine/__init__.py
neuralengine/config.py
neuralengine/tensor.py
neuralengine/utils.py
neuralengine/nn/__init__.py
neuralengine/nn/dataload.py
neuralengine/nn/layers.py
neuralengine/nn/loss.py
neuralengine/nn/metrics.py
neuralengine/nn/model.py
neuralengine/nn/optim.py
neuralengine-0.4.2.dist-info/licenses/LICENSE
neuralengine-0.4.2.dist-info/METADATA
neuralengine-0.4.2.dist-info/WHEEL
neuralengine-0.4.2.dist-info/top_level.txt
neuralengine-0.4.2.dist-info/RECORD
