Metadata-Version: 2.4
Name: NeuralEngine
Version: 0.4.2
Summary: A framework/library for building and training neural networks.
Home-page: https://github.com/Prajjwal2404/NeuralEngine
Author: Prajjwal Pratap Shah
Author-email: Prajjwal Pratap Shah <prajjwalpratapshah@outlook.com>
Maintainer: Prajjwal Pratap Shah
License: MIT License
Project-URL: Homepage, https://github.com/Prajjwal2404/NeuralEngine
Keywords: deep-learning,neural-networks,machine-learning,numpy,cupy,autograd
Classifier: Programming Language :: Python :: 3
Classifier: Operating System :: OS Independent
Requires-Python: >=3.10
License-File: LICENSE
Requires-Dist: numpy>=1.26.4
Provides-Extra: cuda
Requires-Dist: cupy-cuda12x>=12.0.0; extra == "cuda"
Dynamic: author
Dynamic: home-page
Dynamic: license-file
Dynamic: requires-python
